wdin/__init__.py
wdin/__main__.py
wdin/core.py
wdin/bin/AutoHotkey.exe
wdin/bin/icon.ico
wdin/data/config.json
wdin/data/sounds/inception.mp3
wdin/data/sounds/mgs-alert.mp3
wdin-0.1.1.dist-info/licenses/LICENSE
wdin-0.1.1.dist-info/METADATA
wdin-0.1.1.dist-info/WHEEL
wdin-0.1.1.dist-info/entry_points.txt
wdin-0.1.1.dist-info/top_level.txt
wdin-0.1.1.dist-info/RECORD
