Metadata-Version: 2.4
Name: wdin
Version: 0.1.1
Summary: Watch Dogs Invasion Notifier
Author: Blasman
License: MIT License
Project-URL: Homepage, https://github.com/Blasman/WDIN
Keywords: notifier,automation,gaming,watchdogs
Classifier: Programming Language :: Python :: 3
Classifier: License :: OSI Approved :: MIT License
Classifier: Operating System :: Microsoft :: Windows
License-File: LICENSE
Requires-Dist: requests
Requires-Dist: wmi
Requires-Dist: scapy
Requires-Dist: ahk
Requires-Dist: pygame
Requires-Dist: pynput
Requires-Dist: pywin32
Dynamic: license-file
